MANIFEST.in
README.md
setup.cfg
setup.py
dynamic_window_approach.egg-info/PKG-INFO
dynamic_window_approach.egg-info/SOURCES.txt
dynamic_window_approach.egg-info/dependency_links.txt
dynamic_window_approach.egg-info/requires.txt
dynamic_window_approach.egg-info/top_level.txt
python/cdwa.pxd
python/dwa.c
python/dwa.pyx
src/dwa.c
src/dwa.h